[{"id":8891,"adult":false,"castId":1,"originalName":"John Travolta","popularity":18.082999999999998,"profilePath":"\/sHjkE7GZbKAa9aZeiKrEBhMDT14.jpg","knownForDepartment":"Acting","order":0,"character":"Jack Terry","creditId":"52fe446f9251416c75034971","gender":2,"name":"John Travolta"},{"id":44038,"adult":false,"castId":2,"originalName":"Nancy Allen","popularity":7.96,"profilePath":"\/tASmSzMcMzhZXvashsW5ny9EzLq.jpg","knownForDepartment":"Acting","order":1,"character":"Sally Badina","creditId":"52fe446f9251416c75034975","gender":1,"name":"Nancy Allen"},{"id":12074,"adult":false,"castId":3,"originalName":"John Lithgow","popularity":9.7260000000000009,"profilePath":"\/8Y1sjBdnVR483S8PrnAQzlESwhx.jpg","knownForDepartment":"Acting","order":2,"character":"Burke","creditId":"52fe446f9251416c75034979","gender":2,"name":"John Lithgow"},{"id":11901,"adult":false,"castId":4,"originalName":"Dennis Franz","popularity":5.0380000000000003,"profilePath":"\/nsH6IzL8AivpgBN0oQdYgunYhSy.jpg","knownForDepartment":"Acting","order":3,"character":"Manny Karp","creditId":"52fe446f9251416c7503497d","gender":2,"name":"Dennis Franz"},{"gender":2,"castId":5,"id":73513,"adult":false,"character":"Sam","popularity":0.82299999999999995,"creditId":"52fe446f9251416c75034981","order":4,"knownForDepartment":"Acting","name":"Peter Boyden","originalName":"Peter Boyden"},{"gender":2,"castId":6,"id":73514,"adult":false,"character":"Donahue","popularity":0.59999999999999998,"creditId":"52fe446f9251416c75034985","order":5,"knownForDepartment":"Acting","name":"Curt May","originalName":"Curt May"},{"gender":2,"castId":7,"id":73515,"adult":false,"character":"Det. Mackey","popularity":0.76300000000000001,"creditId":"52fe446f9251416c75034989","order":6,"knownForDepartment":"Acting","name":"John Aquino","originalName":"John Aquino"},{"id":13728,"adult":false,"castId":16,"originalName":"John McMartin","popularity":3.2480000000000002,"profilePath":"\/d1leXuDt0hm6IUDfW6bhtdKV1WN.jpg","knownForDepartment":"Acting","order":7,"character":"Lawrence Henry","creditId":"52fe446f9251416c750349bd","gender":2,"name":"John McMartin"},{"gender":1,"castId":17,"id":22107,"adult":false,"character":"Hooker","popularity":1.415,"creditId":"52fe446f9251416c750349c1","order":8,"knownForDepartment":"Costume & Make-Up","name":"Deborah Everton","originalName":"Deborah Everton"},{"id":12439,"adult":false,"castId":18,"originalName":"J. Patrick McNamara","popularity":1.871,"profilePath":"\/1KsonlufeAkqgdX5L8qge7Yzdhw.jpg","knownForDepartment":"Acting","order":9,"character":"Detective at Hospital","creditId":"52fe446f9251416c750349c5","gender":2,"name":"J. Patrick McNamara"},{"gender":1,"castId":19,"id":1117284,"adult":false,"character":"Coed Lover","popularity":0.59999999999999998,"creditId":"52fe446f9251416c750349c9","order":10,"knownForDepartment":"Acting","name":"Missy Cleveland","originalName":"Missy Cleveland"},{"id":174653,"adult":false,"castId":20,"originalName":"Roger Wilson","popularity":1.8520000000000001,"profilePath":"\/9h2SqEtA3qDuBmnisZguudOoqK1.jpg","knownForDepartment":"Acting","order":11,"character":"Coed Lover","creditId":"52fe446f9251416c750349cd","gender":2,"name":"Roger Wilson"},{"gender":1,"castId":21,"id":197399,"adult":false,"character":"Sue","popularity":1.9410000000000001,"creditId":"52fe446f9251416c750349d1","order":12,"knownForDepartment":"Acting","name":"Lori-Nan Engler","originalName":"Lori-Nan Engler"},{"gender":0,"castId":22,"id":1344729,"adult":false,"character":"Girl Lover","popularity":0.59999999999999998,"creditId":"53d11002c3a368776100a247","order":13,"knownForDepartment":"Acting","name":"Barbara Sigel","originalName":"Barbara Sigel"},{"gender":2,"castId":23,"id":1345867,"adult":false,"character":"Boy Lover","popularity":0.59999999999999998,"creditId":"53d11014c3a368776100a24a","order":14,"knownForDepartment":"Acting","name":"David De Felice","originalName":"David De Felice"},{"id":1209900,"adult":false,"castId":24,"originalName":"Roberto Lombardi","popularity":1.4379999999999999,"profilePath":"\/bvIqGEVBYYJi7jMTXW4cFbMYTfm.jpg","knownForDepartment":"Acting","order":15,"character":"Train Passenger","creditId":"53d11023c3a368776a00a37b","gender":2,"name":"Roberto Lombardi"},{"gender":1,"castId":25,"id":1793542,"adult":false,"character":"Dancing Coed","popularity":1.393,"creditId":"58ff85c992514161e8000796","order":16,"knownForDepartment":"Acting","name":"Missy Crutchfield","originalName":"Missy Crutchfield"},{"id":555067,"adult":false,"castId":31,"originalName":"Cindy Manion","popularity":1.9239999999999999,"profilePath":"\/quqsPk5LIOY4X4YKSFF0TcmYkez.jpg","knownForDepartment":"Acting","order":17,"character":"Dancing Coed","creditId":"5cc487eac3a36820b581d0af","gender":1,"name":"Cindy Manion"},{"gender":0,"castId":32,"id":2298215,"adult":false,"character":"Ecstatic Coed","popularity":0.59999999999999998,"creditId":"5cc48817c3a36809ab89949c","order":18,"knownForDepartment":"Acting","name":"Marcy Bigelman","originalName":"Marcy Bigelman"},{"gender":0,"castId":33,"id":2298216,"adult":false,"character":"Studious Coed","popularity":0.59999999999999998,"creditId":"5cc4884c0e0a265b0ff4c607","order":19,"knownForDepartment":"Acting","name":"Ann Kelly","originalName":"Ann Kelly"},{"gender":0,"castId":34,"id":2298217,"adult":false,"character":"Campus Guard","popularity":0.59999999999999998,"creditId":"5cc4888e0e0a2678a0ebadfb","order":20,"knownForDepartment":"Acting","name":"Dean Bennett","originalName":"Dean Bennett"},{"gender":0,"castId":35,"id":2298219,"adult":false,"character":"Maniac","popularity":0.59999999999999998,"creditId":"5cc488d592514102f9f406c9","order":21,"knownForDepartment":"Acting","name":"John Coppolino Jr.","originalName":"John Coppolino Jr."},{"gender":2,"castId":36,"id":1212524,"adult":false,"character":"Mixer","popularity":0.59999999999999998,"creditId":"5cc489019251415cd2f739ab","order":22,"knownForDepartment":"Acting","name":"Archie Lang","originalName":"Archie Lang"},{"gender":2,"castId":37,"id":2298220,"adult":false,"character":"Anchorman","popularity":0.59999999999999998,"creditId":"5cc489849251417d39035305","order":23,"knownForDepartment":"Acting","name":"Dave Roberts","originalName":"Dave Roberts"},{"gender":0,"castId":38,"id":2298221,"adult":false,"character":"Anchorwoman","popularity":0.59999999999999998,"creditId":"5cc489b4c3a368454a81ddd6","order":24,"knownForDepartment":"Acting","name":"Claire Carter","originalName":"Claire Carter"},{"gender":0,"castId":39,"id":1244526,"adult":false,"character":"Jack Manners","popularity":0.59999999999999998,"creditId":"5cc489f89251413a1cf7182b","order":25,"knownForDepartment":"Acting","name":"Maurice Copeland","originalName":"Maurice Copeland"},{"gender":0,"castId":40,"id":1197478,"adult":false,"character":"Governor McRyan","popularity":0.59999999999999998,"creditId":"5cc48a36c3a36827d583f6f7","order":26,"knownForDepartment":"Acting","name":"John Hoffmeister","originalName":"John Hoffmeister"},{"gender":2,"castId":41,"id":1510618,"adult":false,"character":"Policeman at Hospital","popularity":0.59999999999999998,"creditId":"5cc48abc0e0a2678a0ebb3c7","order":27,"knownForDepartment":"Acting","name":"Thomas J. McCarthy","originalName":"Thomas J. McCarthy"},{"gender":0,"castId":42,"id":2298223,"adult":false,"character":"Policeman at Hospital","popularity":0.59999999999999998,"creditId":"5cc48aee92514102f9f40b53","order":28,"knownForDepartment":"Acting","name":"Reginald M. Wallace","originalName":"Reginald M. Wallace"},{"gender":0,"castId":43,"id":2298224,"adult":false,"character":"Hospital Administrator","popularity":0.59999999999999998,"creditId":"5cc48b129251412ba1f9c6bc","order":29,"knownForDepartment":"Acting","name":"Robert L. Penrose","originalName":"Robert L. Penrose"},{"gender":0,"castId":44,"id":2298225,"adult":false,"character":"Doctor","popularity":0.59999999999999998,"creditId":"5cc48b34c3a36827d583f936","order":30,"knownForDepartment":"Acting","name":"Larry Woody","originalName":"Larry Woody"},{"gender":2,"castId":45,"id":160560,"adult":false,"character":"TV Newscaster","popularity":0.69399999999999995,"creditId":"5cc48b5c0e0a265b0ff4cb99","order":31,"knownForDepartment":"Acting","name":"Dick McGarvin","originalName":"Dick McGarvin"},{"gender":0,"castId":46,"id":2298226,"adult":false,"character":"Newsdealer","popularity":0.59999999999999998,"creditId":"5cc48b7a0e0a265b0ff4cbb1","order":32,"knownForDepartment":"Acting","name":"Michael Borghese","originalName":"Michael Borghese"},{"gender":0,"castId":47,"id":2298227,"adult":false,"character":"Receptionist","popularity":0.59999999999999998,"creditId":"5cc48b8cc3a3681e6b83d79c","order":33,"knownForDepartment":"Acting","name":"Rossana Fichera","originalName":"Rossana Fichera"},{"id":79646,"adult":false,"castId":48,"originalName":"James Jeter","popularity":1.2589999999999999,"profilePath":"\/bktL8UnNggW5CkYysEtP8iU00SG.jpg","knownForDepartment":"Acting","order":34,"character":"Film Lab Man","creditId":"5cc48bb60e0a2649cfed332e","gender":2,"name":"James Jeter"},{"gender":0,"castId":49,"id":2298229,"adult":false,"character":"Freddie Corso","popularity":1.05,"creditId":"5cc48befc3a368454a81e1e5","order":35,"knownForDepartment":"Acting","name":"Luddy Tramontana","originalName":"Luddy Tramontana"},{"gender":0,"castId":50,"id":2298230,"adult":false,"character":"Cop in Car","popularity":0.59999999999999998,"creditId":"5cc48c0d92514102f9f40d72","order":36,"knownForDepartment":"Acting","name":"Sid Doherty","originalName":"Sid Doherty"},{"gender":0,"castId":51,"id":2298231,"adult":false,"character":"Mobster","popularity":0.59999999999999998,"creditId":"5cc48c219251412ba1f9c81e","order":37,"knownForDepartment":"Acting","name":"Milt Fields","originalName":"Milt Fields"},{"gender":2,"castId":52,"id":1720337,"adult":false,"character":"Corrupt Captain","popularity":0.83999999999999997,"creditId":"5cc48c40c3a36827ec81ed77","order":38,"knownForDepartment":"Acting","name":"Bud Seese","originalName":"Bud Seese"},{"gender":0,"castId":53,"id":2298233,"adult":false,"character":"First Murder Victim","popularity":0.59999999999999998,"creditId":"5cc48c66c3a36827ec81edd3","order":39,"knownForDepartment":"Acting","name":"Maureen Sullivan","originalName":"Maureen Sullivan"},{"gender":0,"castId":54,"id":2298235,"adult":false,"character":"Cop at Karp's Office","popularity":0.59999999999999998,"creditId":"5cc48c900e0a2678a0ebb6e6","order":40,"knownForDepartment":"Acting","name":"Brian Corrigan","originalName":"Brian Corrigan"},{"gender":0,"castId":55,"id":2298236,"adult":false,"character":"Screamer","popularity":0.78800000000000003,"creditId":"5cc48cac9251415d3bf29635","order":41,"knownForDepartment":"Acting","name":"Elaine Filoon","originalName":"Elaine Filoon"},{"id":74682,"adult":false,"castId":56,"originalName":"Robin Sherwood","popularity":1.4079999999999999,"profilePath":"\/suEapDhDsMzBWnaAIddfZmuTCH1.jpg","knownForDepartment":"Acting","order":42,"character":"Betty","creditId":"5cc48cd4c3a36820b581d977","gender":1,"name":"Robin Sherwood"},{"id":94998,"adult":false,"castId":57,"originalName":"Tim Choate","popularity":1.5669999999999999,"profilePath":"\/tXMeNloQvJw0HPGOieWpwMieJ6K.jpg","knownForDepartment":"Acting","order":43,"character":"Sailor","creditId":"5cc48d149251415d3bf296d5","gender":2,"name":"Tim Choate"},{"gender":0,"castId":58,"id":2298237,"adult":false,"character":"Sailor's Friend","popularity":0.59999999999999998,"creditId":"5cc48d3ec3a36827d583fd0d","order":44,"knownForDepartment":"Acting","name":"B.J. Cyrus","originalName":"B.J. Cyrus"},{"gender":0,"castId":59,"id":2298238,"adult":false,"character":"Sailor's Friend","popularity":0.59999999999999998,"creditId":"5cc48d56c3a36814588bc096","order":45,"knownForDepartment":"Acting","name":"Dave DeAngelis","originalName":"Dave DeAngelis"},{"gender":0,"castId":60,"id":2298239,"adult":false,"character":"Sailor's Friend","popularity":0.59999999999999998,"creditId":"5cc48d7e9251415cd2f746b4","order":46,"knownForDepartment":"Acting","name":"Thomas Finn","originalName":"Thomas Finn"},{"id":80167,"adult":false,"castId":61,"originalName":"Tony Devon","popularity":2.4940000000000002,"profilePath":"\/o8KsixveQn7inWu4VrjIGt1i4rH.jpg","knownForDepartment":"Acting","order":47,"character":"Sailor's Friend","creditId":"5cc48dbcc3a36814588bc1a6","gender":2,"name":"Tony Devon"},{"gender":0,"castId":62,"id":2298242,"adult":false,"character":"Ambulance Attendant","popularity":0.59999999999999998,"creditId":"5cc48e379251417d39035ae3","order":48,"knownForDepartment":"Acting","name":"Henry Cohen","originalName":"Henry Cohen"},{"id":5297,"adult":false,"castId":63,"originalName":"Bernie Rachelle","popularity":3.1960000000000002,"profilePath":"\/3vLedN68rG9VfUfKyVdNpj39ME7.jpg","knownForDepartment":"Acting","order":49,"character":"Ambulance Attendant","creditId":"5cc48e62c3a36809ab89a15f","gender":2,"name":"Bernie Rachelle"},{"gender":0,"castId":64,"id":2298245,"adult":false,"character":"Security Guard","popularity":0.59999999999999998,"creditId":"5cc48e8b0e0a265b0ff4d105","order":50,"knownForDepartment":"Acting","name":"William Tarman","originalName":"William Tarman"},{"gender":0,"castId":65,"id":2298246,"adult":false,"character":"Hawker","popularity":0.59999999999999998,"creditId":"5cc48ea4c3a36827d583ff9c","order":51,"knownForDepartment":"Acting","name":"Michael Tearson","originalName":"Michael Tearson"}]