[{"id":2895,"adult":false,"castId":34,"originalName":"Emil Jannings","popularity":1.8380000000000001,"profilePath":"\/yX7AFfYgYit6WlPshockLsP40LB.jpg","knownForDepartment":"Acting","order":1,"character":"Immanuel Rath","creditId":"5d7b4863069f0e066f3252cc","gender":2,"name":"Emil Jannings"},{"id":2896,"adult":false,"castId":35,"originalName":"Marlene Dietrich","popularity":4.9160000000000004,"profilePath":"\/gQFppqFeUdJDfKsp4Lh2G7UDd0R.jpg","knownForDepartment":"Acting","order":2,"character":"Lola Lola","creditId":"5d7b4883af432467359663a2","gender":1,"name":"Marlene Dietrich"},{"id":2897,"adult":false,"castId":36,"originalName":"Kurt Gerron","popularity":1.875,"profilePath":"\/1dannHvwMGKxqITWP6VNoR3nwIC.jpg","knownForDepartment":"Acting","order":3,"character":"Kiepert","creditId":"5d7b48a933ec2600127f8e76","gender":2,"name":"Kurt Gerron"},{"id":2898,"adult":false,"castId":37,"originalName":"Rosa Valetti","popularity":1.754,"profilePath":"\/6FkyTtJRJJIkHQbU5G6HLnqOtms.jpg","knownForDepartment":"Acting","order":4,"character":"Guste","creditId":"5d7b48caaf432462b4966415","gender":1,"name":"Rosa Valetti"},{"id":2899,"adult":false,"castId":38,"originalName":"Hans Albers","popularity":1.22,"profilePath":"\/x1s3RdddpAfjNXVhYJqjAskklUV.jpg","knownForDepartment":"Acting","order":5,"character":"Mazeppa","creditId":"5d7b48f4af432442ca96a5cd","gender":2,"name":"Hans Albers"},{"id":2903,"adult":false,"castId":39,"originalName":"Reinhold Bernt","popularity":1.6859999999999999,"profilePath":"\/wXzLxaPuwz3iydULeO3XjSxKqfl.jpg","knownForDepartment":"Acting","order":6,"character":"The Clown","creditId":"5d7b491d069f0e066d324b9d","gender":2,"name":"Reinhold Bernt"},{"id":2911,"adult":false,"castId":40,"originalName":"Károly Huszár","popularity":1.351,"profilePath":"\/pKycwM091e9Ag1kq0U7kSnfqOma.jpg","knownForDepartment":"Acting","order":7,"character":"The Blue Angel's Proprietor","creditId":"5d7b4952069f0e5593314c0c","gender":2,"name":"Károly Huszár"},{"id":2904,"adult":false,"castId":42,"originalName":"Eduard von Winterstein","popularity":0.97999999999999998,"profilePath":"\/fIH6N0IG136FiuJ9ztoI2SYQ4fk.jpg","knownForDepartment":"Acting","order":9,"character":"School Headmaster","creditId":"5d7b49fbaf43246735966622","gender":2,"name":"Eduard von Winterstein"},{"gender":2,"castId":43,"id":2905,"adult":false,"character":"Bedel","popularity":0.59999999999999998,"creditId":"5d7b4a3933ec2600137f9f9e","order":10,"knownForDepartment":"Acting","name":"Hans Roth","originalName":"Hans Roth"},{"gender":0,"castId":44,"id":2906,"adult":false,"character":"Pupil","popularity":0.59999999999999998,"creditId":"5d7b4a78069f0e1470336763","order":11,"knownForDepartment":"Acting","name":"Rolf Müller","originalName":"Rolf Müller"},{"id":2907,"adult":false,"castId":45,"originalName":"Roland Varno","popularity":1.3400000000000001,"profilePath":"\/nJa3meuMc7UrURIB6WzMnHxSYXf.jpg","knownForDepartment":"Acting","order":12,"character":"Pupil","creditId":"5d7b4ab5069f0e066f3256af","gender":2,"name":"Roland Varno"},{"id":2908,"adult":false,"castId":46,"originalName":"Carl Ballhaus","popularity":0.70899999999999996,"profilePath":"\/5lH020LaPsfpcS71KQKzRLsDHHM.jpg","knownForDepartment":"Acting","order":13,"character":"Pupil","creditId":"5d7b4ae5af43243b229852ba","gender":2,"name":"Carl Ballhaus"},{"gender":0,"castId":47,"id":2910,"adult":false,"character":"Pupil","popularity":0.59999999999999998,"creditId":"5d7b4b1aaf432467359667e6","order":14,"knownForDepartment":"Acting","name":"Robert Klein-Lörk","originalName":"Robert Klein-Lörk"},{"id":2912,"adult":false,"castId":48,"originalName":"Wilhelm Diegelmann","popularity":0.82799999999999996,"profilePath":"\/17o74QH3h3YgWvFYe3ryWwgjvmh.jpg","knownForDepartment":"Acting","order":15,"character":"Captain","creditId":"5d7b4ba033ec2600147f9bcf","gender":2,"name":"Wilhelm Diegelmann"},{"id":2913,"adult":false,"castId":49,"originalName":"Gerhard Bienert","popularity":1.2010000000000001,"profilePath":"\/lK3MxrK9LUHxPGvXwcejatLmRPb.jpg","knownForDepartment":"Acting","order":16,"character":"Policeman","creditId":"5d7b4bd933ec2600107f9d34","gender":2,"name":"Gerhard Bienert"},{"gender":1,"castId":50,"id":2914,"adult":false,"character":"Maid","popularity":0.59999999999999998,"creditId":"5d7b4c2d33ec2600127f93a3","order":17,"knownForDepartment":"Acting","name":"Ilse Fürstenberg","originalName":"Ilse Fürstenberg"},{"id":2916,"adult":false,"castId":51,"originalName":"Friedrich Hollaender","popularity":0.59999999999999998,"profilePath":"\/mbK3xSgCQg66FF0n9QQv9nIC8TV.jpg","knownForDepartment":"Sound","order":18,"character":"Pianist (uncredited)","creditId":"5d7b4c70af43243b229854b8","gender":2,"name":"Friedrich Hollaender"},{"id":14158,"adult":false,"castId":52,"originalName":"Wolfgang Staudte","popularity":0.83999999999999997,"profilePath":"\/oyFOK4UC279zAiMLeqEWj3Ud9si.jpg","knownForDepartment":"Directing","order":19,"character":"Pupil (uncredited)","creditId":"5d7b4caf33ec2600127f9457","gender":2,"name":"Wolfgang Staudte"},{"gender":0,"castId":65,"id":1941045,"adult":false,"character":"Prostitue (uncredited)","popularity":0.59999999999999998,"creditId":"60802e03955c6500414ebad0","order":20,"knownForDepartment":"Directing","name":"Edith Kiel","originalName":"Edith Kiel"}]