[{"gender":2,"department":"Sound","id":17132,"adult":false,"creditId":"53e10caec3a3686c60003b4c","popularity":2.9209999999999998,"profilePath":"\/8hbT6x1exPiGxqYpt59DkVxRPy.jpg","job":"Music","knownForDepartment":"Sound","name":"Shiro Sagisu","originalName":"Shiro Sagisu"},{"gender":2,"department":"Directing","id":1056311,"adult":false,"creditId":"52fe4b2b9251416c750fa94b","popularity":1.0600000000000001,"job":"Director","knownForDepartment":"Visual Effects","name":"Toshiyuki Kubooka","originalName":"Toshiyuki Kubooka"},{"gender":2,"department":"Writing","id":1067818,"adult":false,"creditId":"52fe4b2b9251416c750fa951","popularity":3.089,"profilePath":"\/u4Kb96qLIMuvMoG4bJMk4zRUJl8.jpg","job":"Novel","knownForDepartment":"Writing","name":"Kentaro Miura","originalName":"Kentaro Miura"},{"gender":2,"department":"Writing","id":1067818,"adult":false,"creditId":"6270816f903c52188363bd9a","popularity":3.089,"profilePath":"\/u4Kb96qLIMuvMoG4bJMk4zRUJl8.jpg","job":"Writer","knownForDepartment":"Writing","name":"Kentaro Miura","originalName":"Kentaro Miura"},{"gender":2,"department":"Writing","id":1144162,"adult":false,"creditId":"5776ad6ac3a36873a1000037","popularity":2.843,"profilePath":"\/bOACJgaqncJOSukAAErIlxBOor8.jpg","job":"Screenplay","knownForDepartment":"Writing","name":"Ichirō Ōkouchi","originalName":"Ichirō Ōkouchi"}]